{"n":"Bierverkostung","s":"Document and manage your personal beer tastings","i":"https://f-droid.org/repo/icons/de.retujo.bierverkostung.4.png","v":"1.1.0","c":["Writing"],"d":"Developed by a beer sommelier, this app allows for managing your personal beer\ntastings. Its functionality comprises the addition, changing and, if necessary,\nthe deletion of\n\n* beers,\n* breweries,\n* beer styles and of course\n* tastings.\n\nBesides the database can be exported and imported as a whole This makes it\npossible to easily migrate the application to another phone. All data resides\nlocally on the phone. An internet connection is thus not required.","src":"https://bitbucket.org/jufickel/bierverkostung/src","lic":"Apache-2.0","web":null,"up":1545868800000,"vc":2}