{"n":"BlackCandy","s":" Black Candy for Android","i":"https://f-droid.org/repo/org.blackcandy.androidApp/en-US/icon_5IpdmBdkZwfEfb4XO5XX7nf6TS-pMgh6wDHW-mdCL3c=.png","v":"2.0.2","c":["Online Media Player"],"d":"Black Candy is an open source, self-hosted music streaming server. With this official mobile app, you can access your music library from your Black Candy server.\n\nTo use this app, you must have a Black Candy server set up. For more information, please visit https://github.com/blackcandy-org/blackcandy","src":"https://github.com/blackcandy-org/app","lic":"MIT","web":null,"up":1778740722978,"vc":7}