{"n":"Shop With Mom","s":"Create price and unit comparisons and create a shopping list.","i":"https://f-droid.org/repo/org.jdfossapps.android.shopwithmom/en-US/icon_PbRa-qLMFp_qfn-Mk1bg3BLZ7taxpL4Ov6yRL-Ctex0=.png","v":"0.0.3","c":["Shopping List"],"d":"An android application that helps you keep track of your shopping list that has a compare the price per unit of diffent items and shows you the best one to get.\n¡Just like shopping with mom!","src":"https://github.com/jdfossapps/shop-with-mom","lic":"GPL-3.0-only","web":null,"up":1776983920317,"vc":3}