{"n":"searxist","s":"Search with SearXNG natively on Android.","i":"https://f-droid.org/repo/xyz.linerly.searxist/en-US/icon_DTFMcrgPGzbTwWVcAKFhkxkmH3C1rmp9RRhEFe78Szc=.png","v":"2026.02.20","c":["Internet"],"d":"<b>searxist</b> <i>(pronounced: searchist)</i> is a simple Android app to wrap SearXNG in a WebView with Material You colors, plus some system integrations.\n\n<b><big>Features</big></b>\n<ul>\n<li>🌙 Material You theming</li>\n<li>🔍 System search integration (search bar widget, popup text action)</li>\n<li>🌐 Choose from public SearXNG instances or add your own</li>\n<li>🛡️ Privacy-focused (no unnecessary data collection!)</li>\n<li>📱 Supports Android 5+</li>\n</ul>\n<b><big>Why would I want to use this?</big></b>\n\nUnlike other search apps, this app uses SearXNG, which is a free and open-source metasearch engine (learn more at https://docs.searxng.org).\n\nWhen you use SearXNG, your search queries get proxied before passing them to various search engines. Not only will you get various results, but it also preserves privacy since the searches aren't directly linked to you.\n\nThe app provides a list of public instances from https://searx.space for you to use. If you have an instance (either that you host yourself or hosted by someone else), you can add it as well.\n\nIf you do use your own instance, make sure other people are also using it to blend in. If the instance is used by only one person, search engines can still link the searches back to you.\n\nThe app does not collect any information; it only passes search queries to the SearXNG instance that you use.\n","src":"https://codeberg.org/searxist/android","lic":"GPL-3.0-or-later","web":"https://searxist.linerly.xyz","up":1777704496684,"vc":20260220}