{"n":"Overchan (fork)","s":"Browse multiple imageboards","i":"https://f-droid.org/repo/icons/bus.chio.wishmaster.1003.png","v":"1.0.3","c":["Forum","Internet"],"d":"Mobile application for browsing imageboards. Supports 4chan, krautchan, 8chan,\niichan.hk, dobrochan, 2ch (russian dvach) and some others.\n\nSome features:\n\n* Separate preferences for each imageboard: password for post deletion, HTTP/SSL, proxy\n* Automatic hide posts and threads using regular expressions\n* Automatic update all open tabs in background\n* Sending posts in background\n* Saving threads with all attachments in HTML with Dollchan\n* Two ways to display replies to posts: as separate references and as list\n* Support the tablet interface\n* Themes\n\nThis is a fork of the original app https://f-droid.org/packages/nya.miku.wishmaster which is no longer\nbeing developed by its author.","src":"https://github.com/AliceCA/Overchan-Android","lic":"GPL-3.0-only","web":"https://miku-nyan.github.io/Overchan-Android","up":1623801600000,"vc":1003,"a":""}