{"n":"Road Trip Radar","s":"A map app prioritizing situational awareness and weather.","i":"https://f-droid.org/repo/ca.voiditswarranty.roadtripradar/en-US/icon_Nrw8KECNxqqJ-Z-AG8uUI9uPsonzgM2_IdgKxrB4r2A=.png","v":"1.13.0","c":["Navigation","Weather"],"d":"RoadTripRadar is a map app prioritizing situational awareness and weather. Live weather radar imagery on an interactive map, helping you see precipitation along your direction of travel at a glance.\n\nFeatures:\n- Distance rings centered on your location that adapt to zoom level.\n- Navigate using bearing to your destination instead of rigid turn-by-turn instructions. Perfect for explorers and people who like to wander!\n- Live animated weather radar from RainViewer with adjustable opacity and playback controls. Perfect for motorcyclists who want notice to reroute around a storm or gear up.\n- Wind speed and direction\n- Temperature and 1-hour trend\n- Multiple map styles: Light, Dark, Auto, and custom colors for either.\n- Speed readout with metric and imperial units, adjustable font size.\n- Open source, no tracking, no accounts, no ads.\n","src":"https://github.com/digiexchris/RoadTripRadar","lic":"MIT","web":"https://github.com/digiexchris/RoadTripRadar/wiki","up":1778872699860,"vc":30,"a":"Chris Chatelain"}