{"n":"OpenVine","s":"Record and stitch 6-second video clips. Offline and private.","i":"https://f-droid.org/repo/ch.betzengineering.openvine/en-US/icon_EkD9OzO1PLAa4Zb27YtJmCGhSr1SdfgYcFuZZd7TPAo=.png","v":"1.0","c":["Camera","Graphics","Multimedia","Recorder"],"d":"OpenVine is a camera app inspired by the mechanics of the classic Vine application. It allows you to create short, looping videos with ease.\n\n<b>Features:</b>\n\n<ul>\n<li>The app records only while you keep the big red button pressed.</li>\n<li>You can release the button to change angles or scenes. Once you have recorded a total of 6 seconds, the app automatically stitches all the clips together into a single video file.</li>\n<li>This is purely a camera utility. There is no external server, no account login, and no cloud tracking.</li>\n<li>Videos are stored locally on your device. You can easily forward them to instant messengers, email, or social networks using the built-in Android share functionality.</li>\n</ul>\n\n<b>Artistic effects:</b>\n\nThe selfie camera may record upside-down on certain devices. This is definitely not a bug but an artistic choice. If you do not want to record upside down, rotate your phone by 180 degrees before recording selfies.\n","src":"https://github.com/michael-betz/OpenVine","lic":"MIT","web":"https://www.betz-engineering.ch","up":1777446141756,"vc":1}