{"n":"Automation","s":"Automate stuff on your device by creating rules.","i":"https://f-droid.org/repo/com.jens.automation2/en-US/icon_HucjkK1EusxOq_XIQ5WpnvoQJVYCHtgjNm-a36Tpbm8=.png","v":"1.8.3","c":["Notification","System"],"d":"Create rules that are made of triggers and actions. A prominent example would be something like \"Mute phone at work\".\n\nHere's a list of supported triggers and actions:\n\nSupported triggers:\n* Location\n* Day/Time\n* Charging state\n* Battery level\n* USB connection to computer established\n* Current speed\n* Background noise (only until Android 7)\n* Wifi connection\n* Other applications running\n* Airplane mode\n* Roaming status\n* NFC tags\n* Activity detection (not in F-Droid version)\n* Bluetooth connection\n* Headset connected\n* Notifications of other apps\n* Device orientation (gyroscope)\n* Profile active or not\n* Screen state (on or off)\n* Status of media playback\n* Device is starting\n* Service is starting\n* Broadcasts of other apps\n* Router state\n* System states (Bluetooth/wifi)\n* Variables that have been set\n* Calendar appointments\n* Phone call running\n\nSupported actions:\n* Change wifi state\n* Change bluetooth state\n* Toggle USB tethering\n* Toggle wifi tethering\n* Toggle Bluetooth tethering\n* Toggle automatic screen rotation\n* Make an HTTP request\n* Change ringtone/sound setting\n* Start another application\n* Wait (in between other actions)\n* Turn screen on or off\n* Toggle airplane mode\n* Toggle mobile data connection\n* Speak text\n* Open music player\n* Control media playback\n* Change screen brightness\n* Play sound file\n* Create notifications\n* Close notifications\n* Send broadcasts\n* Run script/command\n* Maintain screen active\n* Set variables\n* Initiate phone calls\n* Terminate phone calls\n* Copy text to clipboard\n* Make screenshot\n* Change location setting\n* Send text message\n\nIt's quite hard to keep this app working across the many different devices as well as the many changes Android undergoes over the versions. I can test it in the emulator, but that cannot show all bugs.\nSo if a certain feature is not working on your device - let me know. Over the years I have fixed almost all bugs that have been reasonably reported to me. But for that I'm dependent on your input.\n\nIf you have a problem and think about contacting me please\n- update to the latest version first and see if your problem persists there, too.\n- check this list of known problems first: https://server47.de/automation/index.php#knownProblems\n\nDonations are certainly a good, but not the only way to motivate me :-)\n* If you'd like to support me, you can also leave a positive review for the app on Google Play (https://play.google.com/store/apps/details?id=com.jens.automation2).\n* If you like the app, simply some warm words via email are always appreciated.\n* Furthermore I can always use help in translating the app. English, German and some Spanish are among my own skills. Italiano e russo sono già coperti. But everything else is more than welcome.\n* If you have a talent/experience in graphics design and have some ideas for nicer icons let me know.\n* If you have an interesting use-case or found a way to combine triggers and actions to achieve something intriguing and you think it's worth putting it on the examples page (https://server47.de/automation/examples.html), let me know.\n\nExplanation of the many permissions can be found here: https://server47.de/automation/permissions.php","src":"https://git.server47.de/jens/Automation","lic":"GPL-3.0-or-later","web":"https://server47.de/automation/","up":1773135381536,"vc":144,"a":"Jens Schröder"}