{"n":"GAMA","s":"A specialized utility to manage and switch GPU rendering APIs via Shizuku","i":null,"v":"1.3","c":["System"],"d":"GAMA (Graphics API Manager for Android) gives you control over your device's GPU rendering API without requiring root access. Whether you are looking to optimize performance or extend your hardware's lifespan, GAMA makes it simple to switch between Vulkan and OpenGL.\n\nKey Features:\n• ❄️ Lower Temperatures: Reduce heat by optimizing GPU overhead.\n• 🔋 Improved Battery Life: Enhance efficiency through smart rendering choices.\n• 🔓 Zero Risk: 100% Knox-safe and no root required—uses Shizuku for secure command execution.\n• 🛠️ User-Friendly: A beautiful UI designed to replace complex terminal commands.\n• 🤖 Automation: Supports Tasker for automated API switching.\n\nWhilst optimised for the Samsung Galaxy S23 lineup, GAMA is compatible with any modern Android device.","src":"https://github.com/palincat/gama","lic":"MIT","web":null,"up":1774952062648,"vc":11,"a":"Popovici Alin-Cătălin"}