{"n":"Word of the day - Learn a new word every day","s":"Every day a new word to learn, copy and share!","i":"https://f-droid.org/repo/com.saverio.wordoftheday_en/en-US/icon_7kv_o16Ha5bkAlSdrIOSMUvE5YyhyvXCqDaU_FF3WLI=.png","v":"2.0","c":["Reading","Science & Education","Writing"],"d":"<b>Every day</b> the app offers <b>a new word to learn</b>, so you will have a vast vocabulary 😍\nYou can read the definition of the word 📚, its origin / etymology 🗺️, its pronunciation / phonetics (RP-IPA) 🔊.\n\n<b>You can copy or share it as well!</b> 📲\n\n--------\n\n👐‍‍ <i>The app is open-source, and you can find the source code on <a href=\"https://github.com/Sav22999/word-of-the-day\">GitHub</a></i>\n‼️ <i>The app contains advertisements, in this way you can support the developer indirectly.  Either way, you can freely disable those in Settings.</i>","src":"https://github.com/Sav22999/word-of-the-day","lic":"GPL-3.0-only","web":"https://www.saveriomorelli.com/projects/word-of-the-day/","up":1729414161000,"vc":17,"a":"Saverio Morelli"}