{"n":"Firefly III Shortcuts","s":"Application simplifies transactions of FireflyIII","i":"https://f-droid.org/repo/com.mustafacanyucel.fireflyiiishortcuts/en-US/icon_wuQKSX95R5HcCQjG9J23hJpgGKAqlFUMfVbplBqV3qw=.png","v":"1.1.2","c":["Finance Manager"],"d":"A modern Android application that simplifies daily financial transactions with Firefly III, the popular open-source personal finance manager.\n\n- Quick Transaction Shortcuts: Create and use shortcuts for your common financial transactions\n- Quick Run Widget: All the shortcuts can be run from your home screen via the widget; no need to even open the application.\n- Clean UI: Modern Material 3 design with intuitive navigation\n- Secure: Your financial data stays on your device with secure API token storage, obtained by OAuth2\n- Fast Synchronization: Efficient data syncing with Firefly III server\n","src":"https://gitlab.com/mcanyucel/firefly-iii-shortcuts","lic":"MIT","web":null,"up":1744557556000,"vc":3,"a":""}