{"n":"Chitralaya CloudGallery App","s":"Transform Telegram into your personal, unlimited photo cloud storage.","i":"https://f-droid.org/repo/com.akslabs.cloudgallery/en-US/icon_w3ISPNkZop8nml5RoDnVxf9QYhwnIKRZA4pbJmkCXHA=.png","v":"0.5","c":["Gallery","Graphics"],"d":"Never Lose a Precious Memory Again! 📸✨\n\nChitralaya CloudGallery (चित्रालय - \"House of Images\" in Sanskrit) is your personal photo fortress that transforms Telegram into unlimited, truly private cloud storage! Say goodbye to the anxiety of losing precious memories and hello to unlimited backup freedom.\n\n🌟 What is CloudGallery?\nChitralaya CloudGallery is a simple open-source Android app\nthat turns your Telegram account into a private photo cloud storage — no signup, no servers, no tracking.\n\nYour photos go straight from your phone to your own Telegram chat,\ngiving you free, practically unlimited backup space with full control over your data.\n\nIt’s not a company or a service — just a open-source tool made by a privacy-minded developer who believes your memories should stay yours.\n\n👋 Hey there!\nI’m Aditya, the guy behind AKS-Labs.\n\nBefore you scroll, let me make one thing clear —\n\nI’m just another user like you, tired of the usual “cloud storage deal” — free at first,\nthen you pay with your money... or even worse, with your privacy.\n\nSo I built something different — Chitralaya CloudGallery.\n\nIt’s not a company, not a service.\nJust a simple, open-source tool —\na bridge between your Android phone 📱 and your Telegram account 📡.\n\n🤔 Why even build this?\nI was using Google Photos like everyone else. Free storage, nice features, AI magic… but then I realized:\n\nGoogle scans my photos to “offer me memories” → which also means they read them.\nGoogle uses user data to personalize services, show relevant ads, improve products,services.\nWe users don’t even know or read what other privacy-concerning terms we’ve agreed to at the time of sign-up.\nAnd will they only use data collected from Google Photos to improve Google Photos — or does it include all Google products?\nSharing a link doesn’t mean it’s private — anyone with that link can see your photos.\nNeeds to compress images when free storage is full.\nOne day, “free storage is full” and they said: “Pay up for more storage.”\nGoogle, builds entire business models around data.\n\nThat’s when it hit me: my photos aren’t mine.\n\nI wanted something unlimited, private, and mine. And then I looked at Telegram.\n\nBut wait… Why Telegram📡? Can’t Telegram see my photos?\nThis is the elephant in the room 🐘.\n“Aditya, you’re asking me to upload my private photos to Telegram. Should I trust them?”\n\nHere’s my honest take:\n\nTelegram encrypts your data in transit, but not end-to-end (like Signal).\nSo if they really wanted to, they could peek.\n\nBut let’s be honest — so can Google, iCloud, OneDrive, or any cloud you don’t run yourself.\n\nThe only way to have absolute control? Run your own server.\nBut not everyone can afford or maintain that.\n\nBut here’s the thing:\n\nTelegram gives insane free cloud storage.\nNo limits (beyond what you can practically upload).\nNo compression if you upload as files.\nAnd their infra is stable enough to trust for years.\nSo it boils down to: who do you want to trust more?\nFor me, Telegram felt like the lesser evil.\n\nBut again — it’s your choice. I’m not telling you to trust Telegram.\nI’m just saying: here’s another option, do with it what you like.\nAnd if you want to dive deeper, check out the FAQ section where I go through all these questions in detail.\n\nSo my thought was simple:\n👉 If I’m anyway trusting a company, I’d rather trust Telegram (with unlimited space, no ads, no AI snooping)\nthan Google(Google, which builds entire business models around data.).\n\nStill, it’s your call. I’m not here to sell you Telegram. I’m just here to hand you the option.\n\n🛡️ Transparency First\nI don’t want you to blindly trust me either. Here’s how CloudGallery works:\n\nYour bot token & chat ID are stored securely in Android keystore (AES encryption).\nYour photos go directly to your Telegram account — no middle servers.\nI don’t track you, I don’t log you, I don’t even know who uses this app.\nThe app is open source. You can read the code yourself.\nNow, let me be fully transparent about limitations too:\n\nBot API has","src":"https://github.com/AKS-Labs/CloudGallery","lic":"Apache-2.0","web":null,"up":1781610024108,"vc":5,"a":"AKS Labs"}