{"n":"Dutch for AnySoftKeyboard","s":"AnySoftKeyboard Dutch Language pack","i":"https://f-droid.org/repo/com.anysoftkeyboard.languagepack.dutch_oss/en-US/icon_yoBhTv-Z9UBT7TB69fLK6sZGZhkFNC_W4Z1cxDixKT8=.png","v":"4.0.1396","c":["Keyboard & IME"],"d":"Dutch layouts and dictionary for AnySoftKeyboard keyboard app.\n\nThis is an expansion layouts pack for AnySoftKeyboard.\nInstall AnySoftKeyboard first, and then select the desired layout from AnySoftKeyboard Settings->Keyboards menu.\n","src":"https://github.com/AnySoftKeyboard/AnySoftKeyboard","lic":"Apache-2.0","web":"https://anysoftkeyboard.github.io","up":1752589004000,"vc":2908,"a":"Menny Even Danan"}