{"n":"Play NotePad","s":"Robust note-taking app with multimedia and organizational features","i":"https://f-droid.org/repo/com.mshdabiola.playnotepad.foss/en-US/icon_eBEBicSe41XcInf86AqoO-6uNokctXg-sR0-r1NtxqA=.png","v":"1.3.4","c":["Graphics","Note","Reading","Task","Writing"],"d":"Play NotePad: Organize Your Life in Style\n\nStay on top of your personal and professional life with Play NotePad, a feature-rich note-taking app designed for efficiency.\n\nMAIN FEATURES\n\n* Effortless Note Taking: Create and edit text notes, attach photos and drawings, or record audio for on-the-go capture.\n* Enhanced Organization: Categorize notes with labels, set reminders for deadlines, and prioritize tasks with pinning.\n* Visual Appeal: Personalize your note backgrounds with colors and images, and choose between list or column view for easy navigation.\n* Offline Access: Never lose your notes, even without an internet connection.\n* Seamless Collaboration: Share notes via email or messaging for effective teamwork.\n\nPlay NotePad is more than just a notepad - it's your essential companion for managing and organizing your notes in style.\n\n\nSource code:\nhttp://github.com/mshdabiola/notepad\n","src":"https://github.com/mshdabiola/NotePad","lic":"GPL-3.0-or-later","web":null,"up":1738409629000,"vc":134}