{"n":"Phantasialand Wait Times","s":"Live wait times for Phantasialand rides","i":"https://f-droid.org/repo/com.quantum_prof.phantalandwaittimes/en-US/icon_NWD42bsJ9bUVJmU5sgswg_EU0G8rqgfM5jGMEmFhmLk=.png","v":"1.0","c":["Navigation"],"d":"Check current wait times for all rides in <b>Phantasialand Brühl</b>.\n\nThe app is small but way faster and cleaner then the official app.  \nNo ads. No tracking. No account required.\n","src":"https://github.com/ProfessorQuantumUniverse/Phantasialand-Waitingtimes-App","lic":"GPL-3.0-only","web":null,"up":1752243485000,"vc":1}