{"n":"Meditation","s":"An essential meditation timer","i":"https://f-droid.org/repo/com.nyxkn.meditation/en-US/icon_yPGTmK_2koB9HHcYcbNxVlA69GrKW6fDMtYwhd9-VH4=.png","v":"1.3.2","c":["Meditation","Sports & Health","Timer"],"d":"This is a meditation timer. Minimalistic, reliable, and truly elegant.\n\n<b>Features</b>\n\n* Simple, elegant, and intuitive\n* No distractions - only the essential features\n* Beautiful assortment of bell and gong sounds\n* Custom volume adjustment of the bell sounds\n* Reliable countdown timer\n* Pre-meditation delay\n* Intermediate meditation intervals\n* Free and open-source software\n\n<b>Description</b>\n\n<i>Meditation</i> is a truly minimalistic countdown timer for meditation, with a clean user interface and no clutter. The minimalism of the app embodies meditation's actual purpose.\n\nA notable feature of the app is the ability to customize the volume of the notification bells independently of system volume. This allows you to set a predefined volume so that the sounds will reliably play at the same loudness every time. No more mid-meditation worrying that you remembered to turn the volume up!\n\nAnother important feature is for the timer to be as reliable as possible, to ensure an accurate meditation time and prompt ending sound notification.\nThis is achieved by starting a foreground service and disabling battery optimization.\n\nReliability is of extreme importance to a meditation tool in order to eliminate all possible worries about the timer not behaving correctly. Just press the button and start!\n","src":"https://github.com/nyxkn/meditation","lic":"GPL-3.0-only","web":"https://github.com/nyxkn/meditation","up":1734086873000,"vc":1101,"a":"nyxkn"}