{"n":"Gugal","s":"A clean and lightweight web search app.","i":"https://f-droid.org/repo/com.porg.gugal/en-US/icon_M4JBK2j4FktNwck6QEjWaJYQK5KKTFmBZZ_2Db2jqu4=.png","v":"0.8.3","c":["Internet"],"d":"Gugal is a clean and lightweight web search app, with a modern, Material 3/You UI.\n\nIt supports 2 search engines - Google and searx/SearXNG. Developers are free to add more search engines.\n\nTo use Gugal with Google Search you need a CSE ID and API key. Instructions for obtaining both can be found in the app. <b>To get these you have to have a Google account, therefore Google might still link searches to your account. If you want to use a search engine that respects your privacy more, use Gugal with a searx/SearXNG instance.</b>\n\n<i>Google and Google Search are trademarks of Google LLC.</i>\n","src":"https://gitlab.com/narektor/gugal","lic":"GPL-3.0-only","web":null,"up":1758804581000,"vc":24,"a":"Narek"}