{"n":"Colony Control","s":"Management and tracking of ant colonies with NFC and QR.","i":"https://f-droid.org/repo/com.example.controldecolonias/en-US/icon_AOLm8gPb-QapFZCst09BqyEmaB2v4oXDBUziHRkWXK8=.png","v":"1.0","c":["Science & Education"],"d":"Please note: This app is currently only available in Spanish.\nColony Control\nAndroid application for managing and monitoring ant colonies, using technologies such as NFC and QR codes for identification, feeding/care reminders, and environmental data recording.\n\nDescription\nThis application is designed to help ant enthusiasts and caretakers keep detailed records of their colonies. It allows you to:\n• Register colonies with information such as species, date, brood stage (eggs, larvae, pupae, workers), and whether they are diseased.\n• Associate unique identifiers with each colony using NFC tags or QR codes.\n• Scan NFC tags or QR codes to quickly access colony information.\n• Record feeding events and add observation notes.\n• Add photos to each colony's gallery.\n• Schedule reminders (one-time, daily, or every X days) to check on or feed the colonies.\n• Record nests found in the field, including their GPS location (optionally disabled with \"Ninja Mode\").\n• Obtain weather data (temperature, description) using the OpenWeatherMap API based on location (if enabled).\n• Manage a to-do list.\n• Export and import data backups.","src":"https://gitlab.com/hormigas/Controldecolonias","lic":"GPL-3.0-or-later","web":null,"up":1763852106000,"vc":1,"a":"Hormigas"}