{"n":"minedmonero","s":"Companion app for monero miners on supported pools","i":"https://f-droid.org/repo/com.vgorcum.minedmonero/en-US/icon_eMSIDEGNnz4xww-rkIFJ_dt8JLEuLnWKmCDm6ZOQCU0=.png","v":"1.1","c":["Finance Manager"],"d":"This app is written for monero miners participating in a supported pool. You can\nuse it to track how much you've mined, how much has been paid out and how much\nis still due, both in XMR and a fiat currency of choice.","src":"https://gitlab.com/mvgorcum/minedmonero","lic":"GPL-3.0-only","web":"https://gitlab.com/mvgorcum/minedmonero/blob/HEAD/Readme.md","up":1519776000000,"vc":2,"a":""}