{"n":"BeeCount Knitting Counter","s":"Knitting row counter","i":"https://f-droid.org/repo/com.knirirr.beecount/en-US/icon_zeDEsMH0H_gkUqRDRbngOFAsgRi9v7ZSS_3Dba_ASPo=.png","v":"2.7.6","c":["Writing"],"d":"A knitting project helper, with the following features:\n\n* Keep track of several knitting projects.\n* For each project, track several items which need counting, e.g. rows, pattern repeats etc\n* Allow counting up, down and re-setting to zero of these counts.\n* Allow editing of projects to add, remove or change counts after project creation.\n* Link counts together so that one increments another.\n* Set row alerts and cause counts to reset at particular values.\n* Allow backing up and restoring of the entire projects database.","src":"https://github.com/knirirr/BeeCount","lic":"Apache-2.0","web":"https://knirirr.com/beecount","up":1776578058109,"vc":139,"a":"knirirr"}