{"n":"Listen1","s":"Mobile music app for multiple music platforms with play and search support","i":"https://f-droid.org/repo/icons/com.listen1.app.1.png","v":"0.8.1","c":["Multimedia"],"d":"Mobile music app for multiple music platforms with play and search support. Current version supports Netease Music, QQ Music, and Xiami Music. Playlist management is also supported. Developed with React Native. Distributed under MIT license.\n\nFeatures:\n\n    * One app for multiple music platforms\n    * Search songs from multiple music platforms\n    * Browse and play playlist on multiple music platforms\n    * Add your favorite music to your own playlist\n    * Night mode\n    * Backup and restore (importing data from Listen1 chrome extension supported)\n","src":"https://github.com/listen1/listen1_mobile","lic":"MIT","web":"https://listen1.github.io/listen1","up":1615420800000,"vc":1,"a":""}