{"n":"Look4Sat: Satellite tracker","s":"Satellite tracker and pass predictor for Android","i":"https://f-droid.org/repo/com.rtbishop.look4sat/en-US/icon_DpPzjvMQA3vX_KwU-T6LDduqdjopZ9CzUtftTm3G9Is=.png","v":"4.1.0","c":["Science & Education"],"d":"Track satellite passes with ease!\n\nThanks to Celestrak and SatNOGS you have access to over 9000 active satellites.\nYou can search the entire database by NORAD Catalog Number or the satellite's name.\n\nOrbital positions and passes are calculated relative to your location.\nTo get reliable data make sure to set the station position via the app Settings.\n\nThe application is built using Kotlin, Coroutines, Jetpack Compose and Navigation.\nIt is now and always will be completely ad-free and open-source.\n\n<b>Main features:</b><ul>\n<li>Predicting satellite positions and passes for up to 10 days</li>\n<li>Showing the list of currently active and upcoming satellite passes</li>\n<li>Showing the active pass progress, polar trajectory and transceivers info</li>\n<li>Showing the satellite positional data, footprint and ground track on the map</li>\n<li>Custom TLE satellite data import is available via Three Line Element .txt files</li>\n<li>Offline first: calculations are made offline. Weekly TLE data update is recommended.</li></ul>\n","src":"https://github.com/rt-bishop/Look4Sat","lic":"GPL-3.0-or-later","web":null,"up":1773048772000,"vc":410,"a":"Arty Bishop"}