{"n":"HomeFeed - RSS Widget","s":"HomeFeed is a customizable RSS feed widget","i":"https://f-droid.org/repo/com.byterdevs.rsswidget/en-US/icon_Nzru2991TIQkYn8eIBcNjvSaH1cn19wuO0wR4Lnp7QA=.png","v":"1.4.1","c":["Internet","News"],"d":"<b>HomeFeed</b> is a customizable RSS feed widget.\n\n<b>Key Features:</b>\n\n• <b>Multi-Feed Support:</b> Consolidate multiple RSS feeds into a single, unified widget for a centralized news experience.\n• <b>Integrated Reader Mode:</b> Access article content through a distraction-free popup, allowing for quick reading without switching applications.\n• <b>Rich Media Support:</b> High-quality image integration enhances the visual presentation of your feeds.\n• <b>Material You Design:</b> Full support for Material Design 3 and dynamic coloring, automatically adapting to your system wallpaper and theme.\n\n<b>Customization & Controls:</b>\n\n• <b>Visual Flexibility:</b> Adjust widget opacity, customize headers, and toggle the visibility of article descriptions or sources to match your preference.\n• <b>Reading Management:</b> Optional dimming for read articles and flexible timestamp formats (relative or absolute).\n• <b>Advanced Refreshing:</b> Set custom background refresh intervals or use a manual refresh button, which can be hidden for a more minimalist look.\n• <b>Data Persistence:</b> Built for reliability with local data storage and optimized network handling.","src":"https://github.com/byter11/rss-widget","lic":"Apache-2.0","web":null,"up":1782808218111,"vc":6,"a":"Mohsin Shaikh"}