{"n":"Catalan for AnySoftKeyboard","s":"Catalan Language Pack for AnySoftKeyboard","i":"https://f-droid.org/repo/com.anysoftkeyboard.languagepack.catalan/en-US/icon_Yk-AFtQNmWoEqjfiNFcxCS7FxvrEX3R9tx-E7G0UXXA=.png","v":"5.1.6158","c":["Keyboard & IME"],"d":"AnySoftKeyboard keyboards pack:\nCatalan keyboard layout.\n* Dictionary now support inner-word \"·\"\n\nThis is an expansion layouts pack for AnySoftKeyboard.\nInstall AnySoftKeyboard first, and then select the desired layout from AnySoftKeyboard Settings->Keyboards menu.","src":"https://github.com/AnySoftKeyboard/AnySoftKeyboard","lic":"Apache-2.0","web":"https://anysoftkeyboard.github.io","up":1752588996000,"vc":6158,"a":"Menny Even Danan"}