{"n":"Ril Control","s":"Control the RIL-daemon process","i":"https://f-droid.org/repo/icons/com.alaskalinuxuser.rilcontrol.1.png","v":"1.0","c":["System"],"d":"This app allows you to stop or start the ril-daemon process on your Oreo\nAndroid phone with the tap of a button.\n\nIt is primarily made for the LG G4 users on the AOSCP Oreo rom, but may work\nfor other purposes.\n\nThis app requires ROOT permission.","src":"https://gitlab.com/alaskalinuxuser/app_ril_control","lic":"Apache-2.0","web":"https://gitlab.com/alaskalinuxuser/app_ril_control","up":1536624000000,"vc":1}