{"n":"Birthday Countdown","s":"An App counting down to your next birthday!","i":"https://f-droid.org/repo/de.drmaxnix.birthdaycountdown/en-US/icon_TxGNjLWY7FKXwwAFEV8bHHgRjt4kY6tO3Ey__VFQx5M=.png","v":"1.1.2","c":["Calendar & Agenda"],"d":"Birthday Countdown is a Free and Open Source App for Android Phones counting down to your next birthday.\n\nCan't await your next birthday? Me neither! So I built this Countdown App for you ^^\n~ Kim &lt;33\n\n<b>Features</b>\n<ul><li>Customizable birth date</li><li>Countdown to next birthday</li><li>Milestones on the way to next birthday</li></ul>\n","src":"https://git.tjdev.de/DrMaxNix/birthdaycountdown","lic":"MIT","web":"https://birthdaycountdown.drmaxnix.de","up":1778568037154,"vc":4,"a":"DrMaxNix"}