{"n":"NC Passwords","s":"A password manager app for Nextcloud's Passwords app","i":"https://f-droid.org/repo/de.jbservices.nc_passwords_app/en-US/icon_QenBW63YS2qEPeBpo-loLXIGIQ3xrtP6KcH_dMH_ra0=.png","v":"21.12.0","c":["Connectivity","Internet","Password & 2FA","Security","System"],"d":"Features\n\n    * View your passwords (with quick copy to clipboard functionality)\n    * Create/Update/Delete your passwords\n    * Autofill Support on Android\n    * View/Set/Unset your favorites\n    * Fast search of your passwords\n    * View your passwords in folder view\n    * Optional Local Biometric Authentication\n    * Local cache of your passwords (if you have no current internet connection)\n    * Nextcloud theming\n    * Displaying the logos of supported websites for saved passwords","src":"https://gitlab.com/joleaf/nc-passwords-app","lic":"Apache-2.0","web":null,"up":1676924516000,"vc":20}