{"n":"SambaLite","s":"A lightweight, modern, and open-source Android client for SMB/CIFS shares.","i":"https://f-droid.org/repo/de.schliweb.sambalite/en-US/icon_K7rWkSBvN35lzCgCBwmNgPckbZgs91a8OhEndKLhbN8=.png","v":"2.5.2","c":["Cloud Storage & File Sync","Connectivity"],"d":"SambaLite is a lightweight, modern, and open-source Android client for SMB/CIFS shares (Samba).\nIt is designed as a minimalist, reliable, and secure tool for accessing SMB shares on your local network – without ads, tracking, or unnecessary features.\n\nSambaLite is a file client, not a system-level filesystem. It focuses on accessing and transferring files, not on providing a mounted network drive.\n\nThe app is intended for tech-savvy users who prefer a lean, transparent solution and value privacy and open source.\n\nMain features:\n\n• Manage connections: SMB server (hostname/IP), share/path, username, password, optional domain\n• Multiple connections with custom names\n• Connection testing with clear error messages\n• Secure credential storage (Android Keystore)\n• File browser with name, type, size, and modification date\n• Pull-to-refresh\n• Sorting (name, date, size)\n• File operations: download, upload, delete, rename\n• File properties\n• Dark/Light mode (system default)\n\nCompatibility:\n\n• Supports modern SMB2/SMB3 servers\n• SMB1 is not supported (deprecated and insecure)\n\nSecurity & Privacy:\n\n• No telemetry or third-party connections\n• No unencrypted storage of sensitive data\n• Credentials stored securely using the Android Keystore\n\nPermissions:\n\nSambaLite only requests the permissions required for its functionality:\n\n• Network access (SMB communication)\n• Access to user-selected storage locations (via Android system file picker)\n• Foreground service and notifications (for reliable background transfers and progress display)\n\nNo data is collected or transmitted to third parties.\n\nSambaLite provides a modern, minimal, and privacy-friendly way to access SMB shares on Android – focused on reliability and transparency.","src":"https://github.com/egdels/SambaLite","lic":"Apache-2.0","web":"https://egdels.github.io/SambaLite/","up":1783922657952,"vc":20502}