{"n":"Sound Quick Settings","s":"A simple Quick Settings Tile to control the sound volume.","i":"https://f-droid.org/repo/fr.smarquis.soundquicksettings/en-US/icon_rlAjGQFt3b1mdjkTYDJvou3wpW17xyBt-nbbujOndrU=.png","v":"1.0.5","c":["Volume"],"d":"1. Add the Tile in the Quick Settings panel.\n2. Tap the Tile to show the volume slider.\n3. Long press the Tile to open the Sound panel.\n\n<u>Note:</u> Don't look for a launcher icon, this app only provides a Quick Settings Tile.\n\nOpen Source project hosted on GitHub: https://github.com/SimonMarquis/Android-SoundQuickSettings","src":"https://github.com/SimonMarquis/Android-SoundQuickSettings","lic":"Apache-2.0","web":null,"up":1730816275000,"vc":10500}