{"n":"FastLyrics","s":"An app that downloads lyrics for the song, you're listening to ","i":"https://f-droid.org/repo/io.github.teccheck.fastlyrics/en-US/icon_Fho2Smns1C1ZpUJp6G0N5Aqjjvk5njBzJGVqQwua1kw=.png","v":"0.6.2","c":["Lyrics"],"d":"FastLyrics is an app that downloads lyrics for the song, you're listening to.\nIt saves lyrics for offline use and even faster access.\n","src":"https://github.com/TecCheck/FastLyrics","lic":"GPL-3.0-only","web":null,"up":1737894146000,"vc":11,"a":"TecCheck"}