{"n":"CPU Stats","s":"Compact CPU Usage Monitor","i":null,"v":"2.2.0","c":["System"],"d":"Simple tool that displays usage details of the CPU within the statusbar.\n\nFeatures:\n* 6 & 8 Core CPU Support!! (2 notification icons)\n* Single Core, Dual Core (NVIDIA Tegra 2), & Quad Core (NVIDIA Tegra 3) support!!\n* Statusbar notification for CPU Usage\n* Statusbar notification for CPU Frequency","src":"https://github.com/takke/cpustats","lic":"Apache-2.0","web":null,"up":1721383604000,"vc":24,"a":"Panecraft, Inc."}