{"n":"Personal Stuff","s":"App used to track, manage and remind you of your own stuff.","i":"https://f-droid.org/repo/m.co.rh.id.a_personal_stuff/en-US/icon_ksxV4Iw6cEKktJ74LSwPauCL0m-GzdrimXdceeLPSgU=.png","v":"1.3.1","c":["Calendar & Agenda","Inventory","Task"],"d":"App used to track, manage and remind you of your own stuff.\nSometimes we forgot where to put something somewhere or forgot when something is going to expire.\nit could be your cooked food that have short expiry or maybe raw meat or chicken that people forgot to cook or even dispose them from refrigerator, or could be anything with expiry or need action that you store somewhere and forgot about it.\nHaving calendar events to all of these doesn't really solve problems, because it can be a lot of things to put in and you do not want to mix important events with your raw meat expiration events.\nHaving todo list app or notes also not much helpful since it was meant to be as generic as possible.\n  similar to like warehouse logistics system but more to personal.\n\nFeatures of this app:\n<ul>\n  <li>Allow user to manage item easily</li>\n  <li>Setup notification to remind you of something</li>\n  <li>Allow user to manage the amount and reminder of the items to keep track of the item.</li>\n  <li>Support barcode scan as input & search</li>\n  <li>Backup and restore app data with ZIP format including images and thumbnails</li>\n  <li>Available in 9 languages (English, German, Estonian, French, Indonesian, Icelandic, Italian, Norwegian Bokmål, Norwegian Nynorsk, Romansh)</li>\n</ul>","src":"https://github.com/rh-id/a-personal-stuff","lic":"GPL-3.0-only","web":null,"up":1781040519859,"vc":15,"a":"rh-id"}