{"n":"Voki Bot","s":"Android automation tool","i":"https://f-droid.org/repo/net.canvoki.vokibot/en-US/icon_X87z5OOX_9zpuRpnv4Fgua0tzt8Y3Bt_V3VvD4TIQKQ=.png","v":"0.7.0","c":["System"],"d":"Makes your Android device perform actions (commands) whenever something happens (triggers).\n\nImplemented triggers:\n\n- NFC tags (configure by tapping)\n- Shortcuts (creates launcher icons)\n- Bluetooth device (on connect to it)\n\nImplemented commands:\n\n- Activate application components: Activities, Services, Receivers\n- Open system configuration pages\n- Connect or disconnect Bluetooth devices","src":"https://github.com/vokimon/vokibot","lic":"AGPL-3.0-or-later","web":"https://vokibot.canvoki.net","up":1782987983975,"vc":70000,"a":"David García Garzón"}