{"n":"OsmAnd~","s":"Global Mobile Map Viewing & Navigation for Offline and Online OSM Maps","i":"https://f-droid.org/repo/net.osmand.plus/en-US/icon_R5cswkpVpZLwTsPD855ukLX_czuOczFwZLn7pCxaB-k=.png","v":"5.3.8","c":["Navigation"],"d":"OsmAnd is an offline world map application based on OpenStreetMap (OSM), which allows you to navigate taking into account the preferred roads and vehicle dimensions. Plan routes based on inclines and record GPX tracks without an internet connection.\nOsmAnd is an open source app. We do not collect user data and you decide what data the app will have access to.\n\nMain features:\n\nMap view\n• Choice of places to be displayed on the map: attractions, food, health and more;\n• Search for places by address, name, coordinates, or category;\n• Map styles for the convenience of different activities: touring view, nautical map, winter and ski, topographic, desert, off-road, and others;\n• Shading relief and plug-in contour lines;\n• Ability to overlay different sources of maps on top of each other;\n\nGPS Navigation\n• Plotting a route to a place without an Internet connection;\n• Customizable navigation profiles for different vehicles: cars, motorcycles, bicycles, 4x4, pedestrians, boats, public transport, and more;\n• Change the constructed route, taking into account the exclusion of certain roads or road surfaces;\n• Customizable information widgets about the route: distance, speed, remaining travel time, distance to turn, and more;\n\nRoute Planning and Recording\n• Plotting a route point by point using one or multiple navigation profiles;\n• Route recording using GPX tracks;\n• Manage GPX tracks: displaying your own or imported GPX tracks on the map, navigating through them;\n• Visual data about the route - descents/ascents, distances;\n• Ability to share GPX track in OpenStreetMap;\n\nCreation of points with different functionality\n• Favourites;\n• Markers;\n• Audio/video notes;\n\nOpenStreetMap\n• Making edits to OSM;\n• Updating maps with a frequency of up to one hour;\n\nAdditional features\n• Compass and radius ruler;\n• Mapillary interface;\n• Night theme;\n• Wikipedia;\n• Large community of users around the world, documentation, and support;\n\nExtra Features:\n\nMaps+\n• Unlimited map downloads;\n• Topo data (Contour lines and Terrain);\n• Nautical depths;\n• Offline Wikipedia;\n• Offline Wikivoyage - Travel guides.\n\nOsmAnd Pro\n• Cross-platform;\n• Hourly map updates;\n• Weather plugin;\n• Elevation widget;\n• Customise route line;\n• Online Elevation profile.\n\nAnti-Features:\n* NonFreeAssets - Artwork, layouts and prerecorded voices are under a non-commercial license\n* NonFreeNet - May use maps and download images from non-free online services\n* Tracking - An unique installation ID is sent alongside map download requests, https://github.com/osmandapp/OsmAnd/issues/15058\n* UpstreamNonFree: Build removes Google Billing and In-app purchase, Amazon In-app purchase, Google ratings, Telegram integration, Google Location, ANT+ integration, pre-built binary deps are rebuilt from source\n","src":"https://github.com/osmandapp/Osmand","lic":"GPL-3.0-only","web":"https://osmand.net","up":1778507335350,"vc":530801,"a":""}