{"n":"Shorty","s":"Shortcuts for Intent Radio or VLC","i":"https://f-droid.org/repo/org.billthefarmer.shorty/en-US/icon_993kgmAR_Z135n1GqS3mKX2COgUfqrZZncA8JDMiQB8=.png","v":"1.16","c":["Multimedia","Radio"],"d":"Create shortcuts for Intent Radio or VLC\n\n* Create shortcuts from the app or the launcher\n* Defaults to BBC Radio 4 if no data entered\n* Look up stations from a list\n* Save and restore list from storage\n* Import list from CSV file\n\n","src":"https://github.com/billthefarmer/shorty","lic":"GPL-3.0-only","web":null,"up":1663459200000,"vc":116,"a":"Bill Farmer"}