{"n":"Memo Game (Privacy Friendly)","s":"(SECUSO) Privacy friendly card game to find pairs of cards","i":"https://f-droid.org/repo/org.secuso.privacyfriendlymemory/en-US/icon__8fNcQhCuCia954Ya-cQ1bF03Ivnzp7F-G4OIw28tSM=.png","v":"1.1.1","c":["Educational Game"],"d":"\nPrivacy Friendly Memo Game is a card game. The goal is to find the same cards in one turn. It belongs to the Privacy Friendly Apps group developed by the research group SECUSO at Karlsruhe Institute of Technology. More information can be found an secuso.org/pfa\n\nThe application provides two predefined card decks, as well as the option to select own images from your device.\nIn addition to a single player mode, it is also possible to play in a dual player mode.\n\nPrivacy Friendly Memo Game has three difficulty level:\n1. a game field with 4x4 cards (overall 16 cards)\n2. a game field with 6x6 cards (overall 36 cards)\n3. a game field with 8x8 cards (overall 64 cards)\n\nWhat makes Privacy Friendly Memo Game different from other similar apps?\n\n1. No permissions\nPrivacy Friendly Memo Game does not require any permissions. The selection of images is done by a task to the gallery so the app does not have any access to the device's storage without the user's control and interaction.\n\nFor comparison: The Top Ten of similar apps from the Google Play Store requires an average of 3,9 permissions (in September 2016). These are for instance the access to the network.\n\n2. No advertisement\nMany other free apps in the Google Play Store dazzle annoying advertising and also shortens battery life.\n\n\nFeel free to contact us via:\nBluesky - @secusoresearch.bsky.social https://bsky.app/profile/secusoresearch.bsky.social\nMastodon - @SECUSO_Research@bawü.social https://xn--baw-joa.social/@SECUSO_Research/\nJob opening - https://secuso.aifb.kit.edu/english/Job_Offers.php","src":"https://github.com/SecUSo/privacy-friendly-memo-game","lic":"GPL-3.0-only","web":"https://secuso.aifb.kit.edu/english/Memo_Game.php","up":1753701502000,"vc":8,"a":"SECUSO - Security Usability Society"}