{"n":"Food Scale Droid","s":"Scale prices to common base units","i":"https://f-droid.org/repo/icons/tmendes.com.analyticalbalancedroid.3.png","v":"1.2","c":["Market & Price","Sports & Health"],"d":"For that time when you go to the market and you buy many small packs of\ndifferent weight prices and different weights you end up a bit lost.\n\nWrite down the Price/Kg, the weight you are taking for each pack and this app\nwill give you the final amount that you have to pay.","src":"https://gitlab.com/tmendes/FoodScaleDroid","lic":"GPL-3.0-only","web":null,"up":1487894400000,"vc":3,"a":"Thiago Mendes"}