{"n":"Xeonjia: Ice Adventures","s":"Save the world by solving ice puzzles and defeating enemies!","i":"https://f-droid.org/repo/xyz.deepdaikon.xeonjia/en-US/icon_1bqqbKPRcCv_2pm6z8W2kKzjDnmSBDCiDNEY5krl_og=.png","v":"3.0.4","c":["Puzzle Game"],"d":"<b>Xeonjia</b> is an <b>adventure game</b> set in a <b>frozen world</b>.\n\nThe floor is frozen! Think carefully about your moves because you can't change direction until you meet an obstacle.\nUse you mind to solve the ice slide puzzles!\n\nThe world has been frozen by the <b>“King of Evil”</b> and it’s no longer a safe place.\n\nLegend has it that a brave hero will defeat the King of Evil and save the kingdom… For this reason every year a person is appointed as “hero” and sent on a journey to try to save it.\n\nNow it's your time, <b>you have been chosen as this year’s hero!</b> Will you be able to defeat the King of Evil?\n\nYou will have to travel the world, explore cities, dungeons and mystical caves.\n\n<b>Are you ready to solve quests and puzzles in this frozen RPG world?</b>\n\nOver time, you will gain experience points that will allow you to increase your level and you will find money and hidden treasures that you can use to buy stuff and improve yourself.\n\nBe careful, the world is full of <b>dangerous enemies</b> ready to attack you!\n\nKeep in mind that most of <b>the floor is frozen</b>, so you can’t stop yourself until you reach a wall, a boulder, or any other type of obstacle.\n\n<b>Use your mind to figure out the best path!</b>","src":"https://gitlab.com/deepdaikon/Xeonjia/tree/HEAD","lic":"GPL-3.0-or-later","web":"https://gitlab.com/deepdaikon/Xeonjia","up":1730816556000,"vc":21,"a":"DeepDaikon"}